fibermagic/__init__.py
fibermagic/_version.py
fibermagic/IO/NeurophotometricsIO.py
fibermagic/IO/__init__.py
fibermagic/core/__init__.py
fibermagic/core/demodulate.py
fibermagic/core/perievents.py
fibermagic/core/plot.py
fibermagic/frontend/__init__.py
fibermagic/frontend/dashboard.py
fibermagic/tests/__init__.py
fibermagic/tests/conftest.py
fibermagic/tests/test_examples.py
fibermagic/utils/__init__.py
fibermagic/utils/independence.py
fibermagic-0.1.4.dist-info/AUTHORS.rst
fibermagic-0.1.4.dist-info/LICENSE
fibermagic-0.1.4.dist-info/METADATA
fibermagic-0.1.4.dist-info/WHEEL
fibermagic-0.1.4.dist-info/entry_points.txt
fibermagic-0.1.4.dist-info/top_level.txt
fibermagic-0.1.4.dist-info/RECORD
