Metadata-Version: 2.1
Name: fibermagic
Version: 0.1.4
Summary: Python package for Fiber Photometry Data Analysis
Home-page: https://github.com/Goreg12345/fibermagic
Author: fibermagic
Author-email: mail@georglange.com
License: BSD (3-clause)
Platform: UNKNOWN
Classifier: Development Status :: 2 - Pre-Alpha
Classifier: Natural Language :: English
Classifier: Programming Language :: Python :: 3
Requires-Python: >=3.7
License-File: LICENSE
License-File: AUTHORS.rst
Requires-Dist: numpy
Requires-Dist: pandas
Requires-Dist: matplotlib
Requires-Dist: scipy
Requires-Dist: scikit-learn
Requires-Dist: plotly
Requires-Dist: dash
